{
    "ShooterBrain": {
        "checkpoints": [
            {
                "steps": 12499974,
                "file_path": "results\\Second\\ShooterBrain\\ShooterBrain-12499974.onnx",
                "reward": -0.0010000000474974513,
                "creation_time": 1777288215.8501382,
                "auxillary_file_paths": [
                    "results\\Second\\ShooterBrain\\ShooterBrain-12499974.pt"
                ]
            },
            {
                "steps": 12999968,
                "file_path": "results\\Second\\ShooterBrain\\ShooterBrain-12999968.onnx",
                "reward": 0.19833333094914754,
                "creation_time": 1777289054.410337,
                "auxillary_file_paths": [
                    "results\\Second\\ShooterBrain\\ShooterBrain-12999968.pt"
                ]
            },
            {
                "steps": 13499972,
                "file_path": "results\\Second\\ShooterBrain\\ShooterBrain-13499972.onnx",
                "reward": 0.17416304491495754,
                "creation_time": 1777289901.9020393,
                "auxillary_file_paths": [
                    "results\\Second\\ShooterBrain\\ShooterBrain-13499972.pt"
                ]
            },
            {
                "steps": 13999975,
                "file_path": "results\\Second\\ShooterBrain\\ShooterBrain-13999975.onnx",
                "reward": 0.1285769224793722,
                "creation_time": 1777290758.5367773,
                "auxillary_file_paths": [
                    "results\\Second\\ShooterBrain\\ShooterBrain-13999975.pt"
                ]
            },
            {
                "steps": 14019302,
                "file_path": "results\\Second\\ShooterBrain\\ShooterBrain-14019302.onnx",
                "reward": 0.12796739245886388,
                "creation_time": 1777290790.7440922,
                "auxillary_file_paths": [
                    "results\\Second\\ShooterBrain\\ShooterBrain-14019302.pt"
                ]
            }
        ],
        "final_checkpoint": {
            "steps": 14019302,
            "file_path": "results\\Second\\ShooterBrain.onnx",
            "reward": 0.12796739245886388,
            "creation_time": 1777290790.7440922,
            "auxillary_file_paths": [
                "results\\Second\\ShooterBrain\\ShooterBrain-14019302.pt"
            ]
        }
    },
    "metadata": {
        "stats_format_version": "0.3.0",
        "mlagents_version": "0.28.0",
        "torch_version": "1.7.1+cu110"
    }
}